snakeye/__init__.py
snakeye/__main__.py
snakeye/cli/__init__.py
snakeye/cli/snakeye.py
snakeye/cli/command/__init__.py
snakeye/cli/command/add_dep.py
snakeye/cli/command/build_project.py
snakeye/cli/command/create_project.py
snakeye/cli/command/list_dep.py
snakeye/cli/command/publish_project.py
snakeye/common/__init__.py
snakeye/common/exception.py
snakeye/common/models.py
snakeye/common/toml.py
snakeye/common/utils.py
snakeye/dep/__init__.py
snakeye/dep/add.py
snakeye/dep/list.py
snakeye/project/__init__.py
snakeye/project/build.py
snakeye/project/create.py
snakeye/project/publish.py
snakeye/template/__init__.txt
snakeye/template/readme.txt
snakeye/template/setup.txt
snakeye/template/license/apache.txt
snakeye/template/license/gpl.txt
snakeye/template/license/mit.txt
snakeye-0.3.dist-info/entry_points.txt
snakeye-0.3.dist-info/LICENSE
snakeye-0.3.dist-info/WHEEL
snakeye-0.3.dist-info/METADATA
snakeye-0.3.dist-info/RECORD
