Metadata-Version: 2.1
Name: snakeye
Version: 0.3
Summary: Python Packaging for Humans
Home-page: https://snakeye.valutac.com
License: UNKNOWN
Author: Rizky Ariestiyansyah
Author-email: onto@valutac.com
Classifier: License :: OSI Approved :: MIT License
Requires-Dist: cleo
Requires-Dist: pytoml
Requires-Dist: flit
